python_countries/__init__.py
python_countries-1.0.1.dist-info/LICENSE
python_countries-1.0.1.dist-info/METADATA
python_countries-1.0.1.dist-info/WHEEL
python_countries-1.0.1.dist-info/top_level.txt
python_countries-1.0.1.dist-info/RECORD
