Metadata-Version: 2.1
Name: python-countries
Version: 1.0.1
Summary: Python bindings for REST Countries API
Home-page: https://github.com/leonkozlowski/python-countries
Author: Leon Kozlowski
Author-email: leonkozlowski@gmail.com
License: UNKNOWN
Keywords: REST Countries API
Platform: UNKNOWN
Classifier: Programming Language :: Python :: 3
Classifier: License :: OSI Approved :: MIT License
Classifier: Operating System :: OS Independent
Requires-Python: >=3.6
Requires-Dist: requests
